BashaFusion/BashaFusion.py
BashaFusion/__init__.py
BashaFusion/iast-token.db
IastFramework/IAST.py
IastFramework/__init__.py
IastFramework/iast-token.db
BashaFusion-0.0.3.dist-info/LICENSE
BashaFusion-0.0.3.dist-info/METADATA
BashaFusion-0.0.3.dist-info/WHEEL
BashaFusion-0.0.3.dist-info/top_level.txt
BashaFusion-0.0.3.dist-info/RECORD
