Metadata-Version: 2.1
Name: BashaFusion
Version: 0.0.3
Summary: A package used to convert indic language to iast & iast to inidc langauge viceversa
Home-page: https://github.com/dankarthik25/BashaFusion
Author: Dan Karthik
Author-email: dankarthik25@gmail.com
License: MIT
Project-URL: Documentation, https://dankarthik25.github.io/BashaFusion
Project-URL: Source, https://github.com/dankarthik25/BashaFusion
Classifier: License :: OSI Approved :: MIT License
Classifier: Programming Language :: Python :: 3.9
Classifier: Operating System :: OS Independent
Requires-Python: >=3.9
License-File: LICENSE
Provides-Extra: dev
Requires-Dist: pytest >=7.0 ; extra == 'dev'
Requires-Dist: twine >=4.0.2 ; extra == 'dev'
